fictional/__init__.py
fictional/py.typed
fictional-0.1.0.dist-info/METADATA
fictional-0.1.0.dist-info/WHEEL
fictional-0.1.0.dist-info/RECORD
