Metadata-Version: 2.4
Name: fictional
Version: 0.1.0
Summary: [WIP] More detail will be added as the package is developed.
Author-email: Hart Traveller <24962209+harttraveller@users.noreply.github.com>
Requires-Python: >=3.13
